dicomsort.py
thedicomsort-1.0.1.dist-info/WHEEL
thedicomsort-1.0.1.dist-info/entry_points.txt
thedicomsort-1.0.1.dist-info/METADATA
thedicomsort-1.0.1.dist-info/RECORD
