Metadata-Version: 2.1
Name: thedicomsort
Version: 1.0.1
Summary: The original best and only project to provide custom sorting and renaming of DICOM files
Author: Steve Pieper
Author-email: pieper@isomics.com
Requires-Python: >=3.7,<4.0
Classifier: Programming Language :: Python :: 3
Classifier: Programming Language :: Python :: 3.7
Classifier: Programming Language :: Python :: 3.8
Classifier: Programming Language :: Python :: 3.9
Classifier: Programming Language :: Python :: 3.10
Classifier: Programming Language :: Python :: 3.11
Requires-Dist: pydicom (>=2.3.1,<3.0.0)
Requires-Dist: tqdm (>=4.64.1,<5.0.0)
